contrastive_xai/__init__.py
contrastive_xai/utils.py
contrastive_xai/grad_cam/__init__.py
contrastive_xai/grad_cam/contrastive_grad_cam.py
contrastive_xai/grad_cam/grad_cam.py
contrastive_xai/lime/__init__.py
contrastive_xai/lime/contrastive_lime.py
contrastive_xai/lime/lime.py
contrastive_xai/lime/lime_contrastive.py
contrastive_xai/lime/my_lime_exp.py
contrastive_xai/lime/utils.py
contrastive_xai/shap/__init__.py
contrastive_xai/shap/contrastive_shap.py
contrastive_xai/shap/shap.py
contrastive_xai-0.1.1.dist-info/LICENSE
contrastive_xai-0.1.1.dist-info/METADATA
contrastive_xai-0.1.1.dist-info/WHEEL
contrastive_xai-0.1.1.dist-info/top_level.txt
contrastive_xai-0.1.1.dist-info/RECORD
