Metadata-Version: 2.1
Name: contrastive-xai
Version: 0.1.1
Summary: Contrastive Explainable AI Algorithms
Home-page: https://github.com/samsonq/contrastive-xai
Author: Samson Qian
Author-email: samsonqian@gmail.com
License: MIT
Keywords: xai explainable-ai contrastive-algorithms
Requires-Python: >=3.6
License-File: LICENSE
